doccov/__init__.py
doccov/main.py
doccov/report.py
doc_cov-0.4.0.dist-info/LICENSE
doc_cov-0.4.0.dist-info/METADATA
doc_cov-0.4.0.dist-info/WHEEL
doc_cov-0.4.0.dist-info/entry_points.txt
doc_cov-0.4.0.dist-info/top_level.txt
doc_cov-0.4.0.dist-info/RECORD
