Metadata-Version: 2.1
Name: doc-cov
Version: 0.4.0
Summary: doc-cov is a tool for measuring docstring coverage of Python project
Home-page: https://github.com/cocodrips/doc-cov
Author: ku-mu
Author-email: cocodrips@gmail.com
License: MIT
Platform: UNKNOWN
Requires-Python: >=3.6
Provides-Extra: dev
Requires-Dist: pytest (>=3) ; extra == 'dev'
